oc_sprint_datetime/__init__.py
oc_sprint_datetime/sprint.py
oc_sprint_datetime-0.1.0.dist-info/LICENSE
oc_sprint_datetime-0.1.0.dist-info/WHEEL
oc_sprint_datetime-0.1.0.dist-info/METADATA
oc_sprint_datetime-0.1.0.dist-info/RECORD
