Metadata-Version: 2.1
Name: oc_sprint_datetime
Version: 0.1.0
Summary: The library with a few useful sprint date and time methods.
Author-email: 0x29a <nk0d6bxt@anonaddy.me>
Requires-Python: >=3.8
Classifier: License :: OSI Approved :: GNU General Public License v3 or later (GPLv3+)
Requires-Dist: jira==3.2.0
Requires-Dist: python-dotenv==0.20.0
Project-URL: Home, https://github.com/0x29a/oc_sprint_datetime
